azure/mgmt/maps/__init__.py
azure/mgmt/maps/_azure_maps_management_client.py
azure/mgmt/maps/_configuration.py
azure/mgmt/maps/_patch.py
azure/mgmt/maps/_serialization.py
azure/mgmt/maps/_vendor.py
azure/mgmt/maps/_version.py
azure/mgmt/maps/py.typed
azure/mgmt/maps/aio/__init__.py
azure/mgmt/maps/aio/_azure_maps_management_client.py
azure/mgmt/maps/aio/_configuration.py
azure/mgmt/maps/aio/_patch.py
azure/mgmt/maps/aio/operations/__init__.py
azure/mgmt/maps/aio/operations/_accounts_operations.py
azure/mgmt/maps/aio/operations/_creators_operations.py
azure/mgmt/maps/aio/operations/_maps_operations.py
azure/mgmt/maps/aio/operations/_patch.py
azure/mgmt/maps/models/__init__.py
azure/mgmt/maps/models/_azure_maps_management_client_enums.py
azure/mgmt/maps/models/_models_py3.py
azure/mgmt/maps/models/_patch.py
azure/mgmt/maps/operations/__init__.py
azure/mgmt/maps/operations/_accounts_operations.py
azure/mgmt/maps/operations/_creators_operations.py
azure/mgmt/maps/operations/_maps_operations.py
azure/mgmt/maps/operations/_patch.py
azure_mgmt_maps-2.1.0.dist-info/LICENSE
azure_mgmt_maps-2.1.0.dist-info/METADATA
azure_mgmt_maps-2.1.0.dist-info/WHEEL
azure_mgmt_maps-2.1.0.dist-info/top_level.txt
azure_mgmt_maps-2.1.0.dist-info/RECORD
